Workbook

Sheet Checklist
A1: SaaS & Cloud AI Security Regulation — Compliance Checklist · 65 controls · v1.0
A2: # | B2: Chapter | C2: Control | D2: Severity | E2: Applies To | F2: Requirement | G2: Verification / Evidence | H2: Status | I2: Owner | J2: Evidence / Notes
A3: 1.1 | B3: Inventory, Discovery & Threat Modeling for AI Systems | C3: AI systems & models inventory and registration | D3: High | E3: SaaS & Cloud | F3: Maintain a central, current inventory of all AI systems — production models, endpoints, agents and datasets — across both tracks. Without it, controls, Shadow-AI detection and incident investigation are impossible. | G3: Monthly reconciliation of the inventory against actual AI resources in each cloud; every active endpoint has a record. | H3: Not Started
A4: 1.2 | B4: Inventory, Discovery & Threat Modeling for AI Systems | C4: Automated Shadow AI discovery | D4: Critical | E4: SaaS | F4: Detect unauthorized employee use of SaaS AI tools via CASB, egress proxy and DNS logs before sensitive data reaches an ungoverned service. | G4: Monthly report of detected AI destinations; each new destination classified approved/blocked within 7 days. | H4: Not Started
A5: 1.3 | B5: Inventory, Discovery & Threat Modeling for AI Systems | C5: Per-system threat modeling (STRIDE + MITRE ATLAS) | D5: High | E5: SaaS & Cloud | F5: Perform dedicated threat modeling for every material AI system, combining STRIDE with ATLAS techniques (prompt injection, data poisoning, model extraction) before production. | G5: A current threat-model document exists for each High-severity system; each threat maps to a mitigating control. | H5: Not Started
A6: 1.4 | B6: Inventory, Discovery & Threat Modeling for AI Systems | C6: Security gates in CI/CD for model deployment | D6: High | E6: Cloud | F6: Embed automated security checks as a mandatory gate in the model deployment pipeline — dependency scanning, artifact-signature verification, permission checks — so deployments that skip the gate are blocked. | G6: No production model deployment bypassed the gate in the last 90 days (pipeline audit log). | H6: Not Started
A7: 2.1 | B7: Data Classification & AI Data-Flow Control | C7: Automated sensitivity labeling in the AI pipeline | D7: High | E7: SaaS & Cloud | F7: Automatically scan and classify data sensitivity in the Data Lake and in prompts before feeding the model, using built-in discovery services. | G7: Every dataset fed to training/RAG passed sensitivity scanning; untagged datasets trend to zero. | H7: Not Started
A8: 2.2 | B8: Data Classification & AI Data-Flow Control | C8: Enforce “what may be sent” policy to SaaS AI | D8: High | E8: SaaS | F8: Technically define which classification levels may be sent to each SaaS AI tool and enforce it inline (not only in written policy). | G8: A proactive block test (test prompt with classified data) is actually blocked; monthly enforcement report. | H8: Not Started
A9: 2.3 | B9: Data Classification & AI Data-Flow Control | C9: Detect and handle personal data in the AI pipeline | D9: Critical | E9: SaaS & Cloud | F9: Detect PII at every point in the pipeline — Lake, prompt, output — and apply handling (block/mask/consent) per PPL Amendment 13. | G9: PII scan on a sample of prompts/outputs confirms zero unauthorized leaks; every PII flow maps to a legal basis. | H9: Not Started
A10: 2.4 | B10: Data Classification & AI Data-Flow Control | C10: Enforce retention/TTL and deletion on AI data | D10: Medium | E10: SaaS & Cloud | F10: Define and enforce automatic retention and deletion policy for prompts, logs, datasets and conversation history. | G10: Data past its retention period is actually deleted (quarterly sampling). | H10: Not Started
A11: 2.5 | B11: Data Classification & AI Data-Flow Control | C11: Training & fine-tuning data lineage (source & origin) | D11: High | E11: Cloud | F11: Document full lineage from the Data Lake to the dataset to the trained model, to detect data poisoning and support investigation. | G11: Every production model has a lineage record back to the Lake source; you can trace which data fed a given model. | H11: Not Started
A12: 3.1 | B12: Technical Controls for SaaS AI Consumption | C12: Enforce SSO/SAML and harden the tenant | D12: High | E12: SaaS | F12: Connect every approved SaaS AI tool to the enterprise IdP (SSO/SAML/SCIM) and disable self-signup, to enforce identity, MFA and central deprovisioning. | G12: No active users without SSO; a departing employee loses access within 24 hours. | H12: Not Started
A13: 3.2 | B13: Technical Controls for SaaS AI Consumption | C13: Block unapproved endpoints at egress proxy/firewall | D13: High | E13: SaaS | F13: Enforce a network-level allowlist of AI destinations so traffic to unapproved destinations is blocked. | G13: An attempt to reach an unapproved AI destination is blocked and logged. | H13: Not Started
A14: 3.3 | B14: Technical Controls for SaaS AI Consumption | C14: Harden the provider: training opt-out, retention, residency | D14: High | E14: SaaS | F14: Provider-side configuration that prevents training on enterprise data, limits retention and ensures compliant residency. | G14: A snapshot of provider settings preserves opt-out + region; verified against the DPA (3.6). | H14: Not Started
... A67: 13.7 | B67: Controls for AI Coding & Development Tools | C67: Govern tool MCP servers and extensions | D67: Medium | E67: SaaS & Cloud | F67: Coding tools connect to MCP servers and plugins that extend their permissions — a supply-chain and excessive-agency vector. | G67: Only approved MCP servers/extensions are connected; each connector's permissions are documented and limited. | H67: Not Started

Sheet Summary
A1: Compliance Summary
A3: By severity | B3: Count | C3: %
A4: Critical | B4: =COUNTIF(Checklist!D3:D67,"Critical") -> 6 | C4: =B4/$B$7 -> 0.092307692
A5: High | B5: =COUNTIF(Checklist!D3:D67,"High") -> 41 | C5: =B5/$B$7 -> 0.63076923
A6: Medium | B6: =COUNTIF(Checklist!D3:D67,"Medium") -> 18 | C6: =B6/$B$7 -> 0.27692308
A7: Total controls | B7: =COUNTA(Checklist!A3:A67) -> 65
A9: By status | B9: Count | C9: %
A10: Not Started | B10: =COUNTIF(Checklist!H3:H67,"Not Started") -> 65 | C10: =B10/$B$7 -> 1
A11: In Progress | B11: =COUNTIF(Checklist!H3:H67,"In Progress") -> 0 | C11: =B11/$B$7 -> 0
A12: Implemented | B12: =COUNTIF(Checklist!H3:H67,"Implemented") -> 0 | C12: =B12/$B$7 -> 0
A13: Verified | B13: =COUNTIF(Checklist!H3:H67,"Verified") -> 0 | C13: =B13/$B$7 -> 0
A14: N/A | B14: =COUNTIF(Checklist!H3:H67,"N/A") -> 0 | C14: =B14/$B$7 -> 0
A15: % complete (Implemented + Verified) | B15: =(B12+B13)/B7 -> 0
A17: By chapter | B17: Count
A18: 1. Inventory, Discovery & Threat Modeling for AI Systems | B18: =COUNTIF(Checklist!A3:A67,"1.*") -> 4
A19: 2. Data Classification & AI Data-Flow Control | B19: =COUNTIF(Checklist!A3:A67,"2.*") -> 5
A20: 3. Technical Controls for SaaS AI Consumption | B20: =COUNTIF(Checklist!A3:A67,"3.*") -> 7
A21: 4. Data Loss Prevention (DLP) on Prompts & Outputs | B21: =COUNTIF(Checklist!A3:A67,"4.*") -> 4
A22: 5. Identities & Permissions | B22: =COUNTIF(Checklist!A3:A67,"5.*") -> 4
A23: 6. Network Security & Isolation | B23: =COUNTIF(Checklist!A3:A67,"6.*") -> 4
A24: 7. Encryption & Secrets Management | B24: =COUNTIF(Checklist!A3:A67,"7.*") -> 4
A25: 8. Model & Agent Security | B25: =COUNTIF(Checklist!A3:A67,"8.*") -> 10
A26: 9. RAG & Model Supply-Chain Security | B26: =COUNTIF(Checklist!A3:A67,"9.*") -> 4
A27: 10. Monitoring, Logging & Detection | B27: =COUNTIF(Checklist!A3:A67,"10.*") -> 4
A28: 11. Evaluation, Testing & Red Teaming | B28: =COUNTIF(Checklist!A3:A67,"11.*") -> 4
A29: 12. Privacy Enforcement & PPL Amendment 13 Compliance | B29: =COUNTIF(Checklist!A3:A67,"12.*") -> 4
A30: 13. Controls for AI Coding & Development Tools | B30: =COUNTIF(Checklist!A3:A67,"13.*") -> 7
